neml-1.5.4.dist-info/top_level.txt
neml-1.5.4.dist-info/RECORD
neml-1.5.4.dist-info/LICENSE
neml-1.5.4.dist-info/METADATA
neml-1.5.4.dist-info/WHEEL
neml/surfaces.cpython-39-x86_64-linux-gnu.so
neml/block.cpython-39-x86_64-linux-gnu.so
neml/libneml.so
neml/hardening.cpython-39-x86_64-linux-gnu.so
neml/uniaxial.py
neml/solvers.cpython-39-x86_64-linux-gnu.so
neml/history.cpython-39-x86_64-linux-gnu.so
neml/visco_flow.cpython-39-x86_64-linux-gnu.so
neml/ri_flow.cpython-39-x86_64-linux-gnu.so
neml/drivers.py
neml/elasticity.cpython-39-x86_64-linux-gnu.so
neml/creep.cpython-39-x86_64-linux-gnu.so
neml/objects.cpython-39-x86_64-linux-gnu.so
neml/axisym.py
neml/damage.cpython-39-x86_64-linux-gnu.so
neml/__init__.py
neml/interpolate.cpython-39-x86_64-linux-gnu.so
neml/models.cpython-39-x86_64-linux-gnu.so
neml/arbbar.py
neml/nemlerror.cpython-39-x86_64-linux-gnu.so
neml/general_flow.cpython-39-x86_64-linux-gnu.so
neml/parse.cpython-39-x86_64-linux-gnu.so
neml/nlsolvers.py
neml/walker.cpython-39-x86_64-linux-gnu.so
neml/larsonmiller.cpython-39-x86_64-linux-gnu.so
neml/math/matrix.cpython-39-x86_64-linux-gnu.so
neml/math/projections.cpython-39-x86_64-linux-gnu.so
neml/math/__init__.py
neml/math/tensors.cpython-39-x86_64-linux-gnu.so
neml/math/nemlmath.cpython-39-x86_64-linux-gnu.so
neml/math/rotations.cpython-39-x86_64-linux-gnu.so
neml/cp/crystaldamage.cpython-39-x86_64-linux-gnu.so
neml/cp/inelasticity.cpython-39-x86_64-linux-gnu.so
neml/cp/kinematics.cpython-39-x86_64-linux-gnu.so
neml/cp/crystallography.cpython-39-x86_64-linux-gnu.so
neml/cp/postprocessors.cpython-39-x86_64-linux-gnu.so
neml/cp/singlecrystal.cpython-39-x86_64-linux-gnu.so
neml/cp/polycrystal.cpython-39-x86_64-linux-gnu.so
neml/cp/sliprules.cpython-39-x86_64-linux-gnu.so
neml/cp/batch.cpython-39-x86_64-linux-gnu.so
neml/cp/__init__.py
neml/cp/slipharden.cpython-39-x86_64-linux-gnu.so
neml/cp/polefigures.py
neml/cp/hucocks.cpython-39-x86_64-linux-gnu.so
neml/cp/generalizedhucocks.cpython-39-x86_64-linux-gnu.so
neml.libs/libneml-40540c89.so
neml.libs/libblas-357956a1.so.3.4.2
