Metadata-Version: 2.1
Name: neml
Version: 1.5.4
Summary: Nuclear Engineering Material model Library
Home-page: https://github.com/Argonne-National-Laboratory/neml
Author: Argonne National Laboratory
Author-email: messner@anl.gov
License: UNKNOWN
Keywords: materials structures modeling
Platform: UNKNOWN
Classifier: Intended Audience :: Science/Research
Classifier: License :: OSI Approved :: MIT License
Classifier: Programming Language :: C++
Classifier: Programming Language :: Python :: 3
Classifier: Operating System :: OS Independent
Requires-Python: >=3.8
